{
    "swagger": "2.0",
    "info": {
        "contact": {}
    },
    "paths": {
        "/api/v1/auth/login": {
            "post": {
                "description": "Authenticate user and return JWT token",
                "consumes": [
                    "application/json"
                ],
                "produces": [
                    "application/json"
                ],
                "tags": [
                    "auth"
                ],
                "summary": "User login",
                "parameters": [
                    {
                        "description": "Login request",
                        "name": "loginRequest",
                        "in": "body",
                        "required": true,
                        "schema": {
                            "$ref": "#/definitions/models.LoginRequest"
                        }
                    }
                ],
                "responses": {
                    "200": {
                        "description": "OK",
                        "schema": {
                            "$ref": "#/definitions/models.LoginResponse"
                        }
                    },
                    "400": {
                        "description": "Bad Request",
                        "schema": {}
                    },
                    "401": {
                        "description": "Unauthorized",
                        "schema": {}
                    }
                }
            }
        }
    },
    "definitions": {
        "models.LoginRequest": {
            "type": "object",
            "properties": {
                "email": {
                    "type": "string"
                },
                "password": {
                    "type": "string"
                }
            }
        },
        "models.LoginResponse": {
            "type": "object",
            "properties": {
                "token": {
                    "type": "string"
                }
            }
        }
    }
}